lmp_sdk/__init__.py
lmp_sdk/asset_integration.py
lmp_sdk/async_infer.py
lmp_sdk/batch_client.py
lmp_sdk/batch_models.py
lmp_sdk/client.py
lmp_sdk/constants.py
lmp_sdk/core.py
lmp_sdk/exceptions.py
lmp_sdk/infer_client.py
lmp_sdk/infer_service.py
lmp_sdk/models.py
lmp_sdk/queue_monitor.py
lmp_sdk/task_processor.py
lmp_sdk/task_queue.py
lmp_sdk-2.0.16.dist-info/METADATA
lmp_sdk-2.0.16.dist-info/WHEEL
lmp_sdk-2.0.16.dist-info/dependency_links.txt
lmp_sdk-2.0.16.dist-info/top_level.txt
lmp_sdk-2.0.16.dist-info/RECORD
